[
  {
    "PlayerName": "Jose",
    "Score": 100,
    "Word": "",
    "AttemptsUsed": 0,
    "AttemptsLeft": 0,
    "Date": "2024-10-01T06:55:25.7348711-07:00"
  },
  {
    "PlayerName": "Jose",
    "Score": 90,
    "Word": "",
    "AttemptsUsed": 0,
    "AttemptsLeft": 0,
    "Date": "2024-10-01T07:08:53.0443123-07:00"
  },
  {
    "PlayerName": "Jose",
    "Score": 90,
    "Word": "polymorphism",
    "AttemptsUsed": 0,
    "AttemptsLeft": 0,
    "Date": "2024-10-01T07:10:52.4710022-07:00"
  },
  {
    "PlayerName": "Jose",
    "Score": 70,
    "Word": "",
    "AttemptsUsed": 0,
    "AttemptsLeft": 0,
    "Date": "2024-10-01T07:05:35.8470054-07:00"
  },
  {
    "PlayerName": "Jose",
    "Score": 60,
    "Word": "",
    "AttemptsUsed": 0,
    "AttemptsLeft": 0,
    "Date": "2024-10-01T06:46:45.7155171-07:00"
  },
  {
    "PlayerName": "Jose",
    "Score": 60,
    "Word": "polymorphism",
    "AttemptsUsed": 13,
    "AttemptsLeft": 2,
    "Date": "2024-10-01T07:13:44.2607135-07:00"
  },
  {
    "PlayerName": "Unknown",
    "Score": 40,
    "Word": "",
    "AttemptsUsed": 0,
    "AttemptsLeft": 0,
    "Date": "2024-10-01T06:50:08.4808801-07:00"
  },
  {
    "PlayerName": "Jose",
    "Score": 40,
    "Word": "",
    "AttemptsUsed": 0,
    "AttemptsLeft": 0,
    "Date": "2024-10-01T06:53:12.3918372-07:00"
  }
]